Metadata-Version: 1.1
Name: bioa
Version: 1.24
Summary: Library for viral diversity estimation and identification using next-gen sequencing data.
Home-page: http://alan.cs.gsu.edu/vira
Author: Nicholas Mancuso et al.
Author-email: nick.mancuso@gmail.com
License: BSD
Download-URL: http://alan.cs.gsu.edu/vira/download
Keywords: viral virus quasispecies bioinformatics next-generation sequencing
Platform: UNKNOWN
Classifier: Development Status :: 4 - Beta
Classifier: Intended Audience :: Science/Research
Classifier: License :: OSI Approved :: BSD License
Classifier: Topic :: Scientific/Engineering :: Bio-Informatics
